carto/__init__.py
carto/api_keys.py
carto/auth.py
carto/datasets.py
carto/do_dataset.py
carto/do_subscription_info.py
carto/do_subscriptions.py
carto/do_token.py
carto/exceptions.py
carto/export.py
carto/fields.py
carto/file_import.py
carto/kuvizs.py
carto/maps.py
carto/paginators.py
carto/permissions.py
carto/resources.py
carto/sql.py
carto/sync_tables.py
carto/synchronizations.py
carto/tables.py
carto/users.py
carto/utils.py
carto/visualizations.py
carto-1.11.2.dist-info/LICENSE
carto-1.11.2.dist-info/METADATA
carto-1.11.2.dist-info/WHEEL
carto-1.11.2.dist-info/top_level.txt
carto-1.11.2.dist-info/RECORD
