Metadata-Version: 2.1
Name: carto
Version: 1.11.2
Summary: SDK around CARTO's APIs
Home-page: https://github.com/CartoDB/carto-python
Author: Daniel Carrión
Author-email: daniel@carto.com
License: UNKNOWN
Platform: UNKNOWN
Requires-Dist: requests (>=2.7.0)
Requires-Dist: pyrestcli (==0.6.11)
